cellart/SSTDataset.py
cellart/__init__.py
cellart/experiment_manager.py
cellart/model.py
cellart/fpn/__init__.py
cellart/fpn/backbone.py
cellart/fpn/containers.py
cellart/fpn/factory.py
cellart/fpn/fpn.py
cellart/fpn/layers.py
cellart/fpn/utils.py
cellart/utils/__init__.py
cellart/utils/io.py
cellart/utils/networks.py
cellart/utils/operate.py
cellart/utils/preprocess.py
cellart/utils/spatialdata_utils.py
cellart-0.0.61.dist-info/licenses/LICENSE
cellart-0.0.61.dist-info/METADATA
cellart-0.0.61.dist-info/WHEEL
cellart-0.0.61.dist-info/top_level.txt
cellart-0.0.61.dist-info/RECORD
