Metadata-Version: 2.4
Name: cellart
Version: 0.0.61
Summary: CellART: a unified framework for extracting single-cell information from high-resolution spatial transcriptomics
Home-page: https://github.com/YangLabHKUST/cellart
Author: Yuheng Chen
Author-email: ychenlp@connect.ust.hk
License: MIT
License-File: LICENSE
Requires-Dist: wandb==0.20.0
Requires-Dist: tensorflow==2.19.0
Requires-Dist: anndata==0.11.4
Requires-Dist: bin2cell==0.3.3
Requires-Dist: distinctipy==1.3.4
Requires-Dist: einops==0.8.1
Requires-Dist: matplotlib==3.7.5
Requires-Dist: numpy==1.26.0
Requires-Dist: opencv_python==4.10.0.84
Requires-Dist: opencv_python_headless==4.8.0.76
Requires-Dist: pandas==2.2.3
Requires-Dist: scanpy==1.11.2
Requires-Dist: scipy==1.13
Requires-Dist: torch==2.0.1
Requires-Dist: torchvision==0.15.2
Requires-Dist: tqdm==4.65.0
Dynamic: author
Dynamic: author-email
Dynamic: home-page
Dynamic: license
Dynamic: license-file
Dynamic: requires-dist
Dynamic: summary
